anant.py
anantmishra-1.0.dist-info/METADATA
anantmishra-1.0.dist-info/WHEEL
anantmishra-1.0.dist-info/top_level.txt
anantmishra-1.0.dist-info/RECORD
