Metadata-Version: 2.1
Name: anantmishra
Version: 1.0
Summary: A simple package for doing calculations
Home-page: UNKNOWN
Author: Anant Mishra
Author-email: gioneemaxuser@gmail.com
License: UNKNOWN
Platform: UNKNOWN
